nonebot_plugin_bilibili_viode/__init__.py
nonebot_plugin_bilibili_viode/config.py
nonebot_plugin_bilibili_viode/img.py
nonebot_plugin_bilibili_viode/main.py
nonebot_plugin_bilibili_viode/models/__init__.py
nonebot_plugin_bilibili_viode/models/bilibili.py
nonebot_plugin_bilibili_viode/models/config.py
nonebot_plugin_bilibili_viode/resource/font/SourceHanSansSC-Bold.otf
nonebot_plugin_bilibili_viode/resource/font/SourceHanSansSC-Light.otf
nonebot_plugin_bilibili_viode/resource/font/SourceHanSansSC-Normal.otf
nonebot_plugin_bilibili_viode/resource/image/0.png
nonebot_plugin_bilibili_viode/resource/image/1.png
nonebot_plugin_bilibili_viode/template/0.yaml
nonebot_plugin_bilibili_viode/template/1.yaml
nonebot_plugin_bilibili_viode/utils.py
nonebot_plugin_bilibili_viode-1.0.1.dist-info/LICENSE
nonebot_plugin_bilibili_viode-1.0.1.dist-info/METADATA
nonebot_plugin_bilibili_viode-1.0.1.dist-info/WHEEL
nonebot_plugin_bilibili_viode-1.0.1.dist-info/RECORD
