Metadata-Version: 2.1
Name: nonebot-plugin-bilibili-viode
Version: 1.0.1
Summary: 一个nonebot2插件，用于获取哔哩哔哩伪分享卡片
Home-page: https://pypi.org/project/nonebot_plugin_bilibili_viode/
License: MIT
Author: ASTWY
Author-email: astwy@outlook.com
Requires-Python: >=3.8.1,<3.12
Classifier: License :: OSI Approved :: MIT License
Classifier: Programming Language :: Python :: 3
Classifier: Programming Language :: Python :: 3.9
Classifier: Programming Language :: Python :: 3.10
Classifier: Programming Language :: Python :: 3.11
Requires-Dist: httpx (>=0.23.3,<0.24.0)
Requires-Dist: nonebot-plugin-guild-patch (>=0.2.3,<0.3.0)
Requires-Dist: nonebot2 (>=2.0.0rc3,<3.0.0)
Requires-Dist: pillow (>=9.4.0,<10.0.0)
Requires-Dist: pyyaml (>=6.0,<7.0)
Requires-Dist: qrcode (>=7.4.2,<8.0.0)
Project-URL: Repository, https://github.com/astwy/nonebot_plugin_bilibili_viode
